PyDebug/__init__.py
PyDebug/__version__.py
PyDebug/base.py
PyDebug/chains.py
PyDebug/colors.py
PyDebug/console.py
PyDebug/converters.py
PyDebug/decorators.py
PythonDebug/__init__.py
PythonDebug/__version__.py
PythonDebug/base.py
PythonDebug/chains.py
PythonDebug/colors.py
PythonDebug/console.py
PythonDebug/converters.py
PythonDebug/decorators.py
PythonDebugTools/__init__.py
PythonDebugTools/__version__.py
PythonDebugTools/base.py
PythonDebugTools/chains.py
PythonDebugTools/colors.py
PythonDebugTools/console.py
PythonDebugTools/converters.py
PythonDebugTools/decorators.py
PythonDebugTools/misc.py
PythonDebugTools-2.2.3.dist-info/LICENSE
PythonDebugTools-2.2.3.dist-info/METADATA
PythonDebugTools-2.2.3.dist-info/WHEEL
PythonDebugTools-2.2.3.dist-info/top_level.txt
PythonDebugTools-2.2.3.dist-info/RECORD
