Metadata-Version: 2.1
Name: PythonDebugTools
Version: 2.2.3
Summary: A set of helpers for debugging Python 3.x.
Home-page: https://github.com/Jakar510/PythonDebugTools
Author: Tyler Stegmaier
Author-email: tyler.stegmaier.510@gmail.com
Maintainer: Tyler Stegmaier
Maintainer-email: tyler.stegmaier.510@gmail.com
License: GPL 3.0
Keywords: switch switch-case case
Platform: UNKNOWN
Classifier: Development Status :: 4 - Beta
Classifier: Intended Audience :: Developers
Classifier: Topic :: Software Development :: Build Tools
Classifier: License :: Free To Use But Restricted
Classifier: Operating System :: MacOS
Classifier: Operating System :: Microsoft :: Windows
Classifier: Operating System :: POSIX
Classifier: Programming Language :: Python :: 3
Requires-Dist: BaseExtensions (>=1.2.5)
